inventree_plugin_creator-1.13.4.dist-info/licenses/LICENSE
plugin_creator/__init__.py
plugin_creator/cli.py
plugin_creator/config.py
plugin_creator/devops.py
plugin_creator/frontend.py
plugin_creator/helpers.py
plugin_creator/mixins.py
plugin_creator/validators.py
plugin_creator/template/cookiecutter.json
plugin_creator/template/hooks/post_gen_project.py
plugin_creator/template/hooks/pre_gen_project.py
plugin_creator/template/hooks/pre_prompt.py
plugin_creator/template/{{ cookiecutter.plugin_name }}/.gitignore
plugin_creator/template/{{ cookiecutter.plugin_name }}/.gitlab-ci.yml
plugin_creator/template/{{ cookiecutter.plugin_name }}/.pre-commit-config.yaml
plugin_creator/template/{{ cookiecutter.plugin_name }}/LICENSE
plugin_creator/template/{{ cookiecutter.plugin_name }}/MANIFEST.in
plugin_creator/template/{{ cookiecutter.plugin_name }}/README.md
plugin_creator/template/{{ cookiecutter.plugin_name }}/biome.json
plugin_creator/template/{{ cookiecutter.plugin_name }}/pyproject.toml
plugin_creator/template/{{ cookiecutter.plugin_name }}/setup.cfg
plugin_creator/template/{{ cookiecutter.plugin_name }}/.github/workflows/ci.yaml
plugin_creator/template/{{ cookiecutter.plugin_name }}/.github/workflows/pypi.yaml
plugin_creator/template/{{ cookiecutter.plugin_name }}/frontend/.gitignore
plugin_creator/template/{{ cookiecutter.plugin_name }}/frontend/.linguirc
plugin_creator/template/{{ cookiecutter.plugin_name }}/frontend/README.md
plugin_creator/template/{{ cookiecutter.plugin_name }}/frontend/index.html
plugin_creator/template/{{ cookiecutter.plugin_name }}/frontend/package.json
plugin_creator/template/{{ cookiecutter.plugin_name }}/frontend/tsconfig.app.json
plugin_creator/template/{{ cookiecutter.plugin_name }}/frontend/tsconfig.json
plugin_creator/template/{{ cookiecutter.plugin_name }}/frontend/tsconfig.node.json
plugin_creator/template/{{ cookiecutter.plugin_name }}/frontend/vite.config.ts
plugin_creator/template/{{ cookiecutter.plugin_name }}/frontend/vite.dev.config.ts
inventree_plugin_creator-1.13.4.dist-info/METADATA
inventree_plugin_creator-1.13.4.dist-info/WHEEL
inventree_plugin_creator-1.13.4.dist-info/entry_points.txt
inventree_plugin_creator-1.13.4.dist-info/top_level.txt
inventree_plugin_creator-1.13.4.dist-info/RECORD
