Metadata-Version: 2.4
Name: inventree-plugin-creator
Version: 1.13.4
Summary: InvenTree plugin creator
Home-page: https://github.com/inventree/plugin-creator
Author: Oliver Walters
Author-email: oliver.henry.walters@gmail.com
License: MIT
Keywords: inventree plugin scaffold
Requires-Python: >=3.9
License-File: LICENSE
Requires-Dist: appdirs
Requires-Dist: cookiecutter
Requires-Dist: license
Requires-Dist: questionary
Dynamic: author
Dynamic: author-email
Dynamic: description
Dynamic: description-content-type
Dynamic: home-page
Dynamic: keywords
Dynamic: license
Dynamic: license-file
Dynamic: requires-dist
Dynamic: requires-python
Dynamic: summary
